Metadata-Version: 2.1
Name: horatio
Version: 0.1.5
Summary: Time your python scripts easily and with style
Home-page: http://github.com/fsossai/horatio
Author: Federico Sossai
Author-email: federico.sossai@gmail.com
